Workbook

Sheet README
A1: Gym Startup Budget Workbook
A2: 2026 — PRO Edition · v1 · refreshed May 2026
A4: How to use this workbook
A5: 1. | B5: Start in the Format & Scenario sheet. Pick your gym format, location tier, and planning scenario. Every other sheet adapts to those inputs.
A6: 2. | B6: Override the defaults. Every cell with blue bold text is a user input — change them to match your actual numbers. Black text is computed via formulas and updates automatically.
A7: 3. | B7: Build your capital stack. The Capital Stack Builder sheet tells you whether your funding sources cover your total need. If the gap is red, you do not have enough capital yet.
A9: License
A10: Single-user license. You may use this workbook for your own gym planning and budgeting. Do not redistribute, resell, or share the file. Reach out if you need a multi-user team license — bill@treetopgrowthstrategy.com.
A12: Built by
A13: Bill Colbert | B13: Founder, Treetop Growth Strategy
A14: Website | B14: https://treetopgrowthstrategy.com
A15: Email | B15: bill@treetopgrowthstrategy.com
A17: Companion content (free)
A18: Workbook | B18: https://treetopgrowthstrategy.com/gym-startup-budget-workbook
A19: Cost guide | B19: https://treetopgrowthstrategy.com/cost-to-start-a-gym
A20: How to open | B20: https://treetopgrowthstrategy.com/how-to-open-a-gym
A21: Financing | B21: https://treetopgrowthstrategy.com/how-to-finance-a-gym
A22: Lease negotiation | B22: https://treetopgrowthstrategy.com/gym-lease-negotiation-guide
A23: Pre-sale playbook | B23: https://treetopgrowthstrategy.com/gym-pre-sale-playbook

Sheet Format & Scenario
A1: Format & Scenario Inputs
A2: Pick your gym format, location tier, and scenario. Every other sheet pulls from these inputs.
A4: Gym format | B4: Small boutique studio
A5: Location tier | B5: Tier 2 (mid metro)
A6: Planning scenario | B6: Realistic
A9: Tier multiplier (auto) | B9: =IF(B5="Tier 1 (NYC/SF/Boston/LA)",1.35,IF(B5="Tier 3 (suburban/rural)",0.80,1.00))
A10: Format base low (auto) | B10: =IF(B4="Personal training studio",45000,IF(B4="Small boutique studio",120000,IF(B4="CrossFit affiliate",80000,IF(B4="Mid-size group fitness",280000,IF(B4="Full-service gym",500000,IF(B4="Boutique franchise",250000,0))))))
A11: Format base high (auto) | B11: =IF(B4="Personal training studio",120000,IF(B4="Small boutique studio",280000,IF(B4="CrossFit affiliate",180000,IF(B4="Mid-size group fitness",550000,IF(B4="Full-service gym",1500000,IF(B4="Boutique franchise",600000,0))))))
A12: Tier-adjusted low | B12: =B10*B9
A13: Tier-adjusted high | B13: =B11*B9
A15: Scenario multiplier (applies to ramp & working-capital assumptions)
A16: Scenario multiplier | B16: =IF(B6="Aggressive",0.7,IF(B6="Conservative",1.3,IF(B6="Stressed",1.6,1.0)))
A18: Working capital months default | B18: =IF(B6="Aggressive",6,IF(B6="Realistic",9,IF(B6="Conservative",12,15)))
A20: Quick estimate (range, tier-adjusted, before working capital)
A21: Estimated total range | B21: =B12 | C21: =B13
A22: Override with computed total from input sheets (see Sensitivity for full model)

Sheet Facility
A1: Facility
A2: Inputs in blue. Buildout net of TI calculated automatically.
A4: Inputs
A5: Square footage | B5: 3500 | D5: Total leased square footage
A6: Base rent per sq ft (annual, NNN) | B6: 35 | D6: Tier 1 metros often $40-80; Tier 2 typically $25-45; Tier 3 $18-32
A7: Buildout cost per sq ft (gross) | B7: 60 | D7: Second-gen retail typical $30-80/sqft
A8: Landlord TI allowance per sq ft | B8: 30 | D8: Negotiate hard. Tier 2/3: $20-40; Tier 1: $40-80
A9: Months security deposit | B9: 3 | D9: Often refundable end-of-lease
A11: Line items (computed)
A12: Security deposit | B12: =(B5*B6/12)*B9
A13: First month rent | B13: =B5*B6/12
A14: Buildout (net of landlord TI) | B14: =B5*MAX(B7-B8,0)
A15: HVAC additions/upgrades | B15: =B5*8
A16: Flooring (rubber, turf, hardwood) | B16: =B5*4
A17: Electrical (cardio + sound + lighting) | B17: =B5*3
A18: Plumbing (locker rooms, water stations) | B18: =B5*3.5
A19: Lighting design + install | B19: =B5*2.5
A20: Signage (exterior + interior) | B20: =5000+(B5/1000)*1500
A21: Architect / designer fees | B21: =B5*4
A22: Facility total | B22: =SUM(B12:B21)
A24: Note: Facility commonly runs 30–50% of total startup cost. Highest-variance category. The TI negotiation alone is often worth $40K–$150K of effectively-free capital — see /gym-lease-negotiation-guide.

Sheet Equipment
A1: Equipment
A2: Pick approach per category from dropdown. Workbook computes immediate cash outlay + 60-month lease obligation.
A4: Category | B4: Approach | C4: Cash now | D4: Monthly (if lease) | E4: 60-mo obligation
A5: Cardio (treadmills, ellipticals, bikes, rowers) | B5: Lease 60mo | C5: =IF(B5="Buy new",G5,IF(B5="Buy used",H5,0)) | D5: =IF(B5="Lease 60mo",I5,0) | E5: =D5*60 | G5: 42000 | H5: 0 | I5: 870
A6: Power racks / squat racks / rigs | B6: Buy used | C6: =IF(B6="Buy new",G6,IF(B6="Buy used",H6,0)) | D6: =IF(B6="Lease 60mo",I6,0) | E6: =D6*60 | G6: 12000 | H6: 6000 | I6: 0
A7: Plates / dumbbells / kettlebells / barbells | B7: Buy used | C7: =IF(B7="Buy new",G7,IF(B7="Buy used",H7,0)) | D7: =IF(B7="Lease 60mo",I7,0) | E7: =D7*60 | G7: 11000 | H7: 5500 | I7: 0
A8: Selectorized machines | B8: Buy used | C8: =IF(B8="Buy new",G8,IF(B8="Buy used",H8,0)) | D8: =IF(B8="Lease 60mo",I8,0) | E8: =D8*60 | G8: 22000 | H8: 8000 | I8: 0
A9: Functional (turf, sleds, mobility) | B9: Buy new | C9: =IF(B9="Buy new",G9,IF(B9="Buy used",H9,0)) | D9: =IF(B9="Lease 60mo",I9,0) | E9: =D9*60 | G9: 7000 | H9: 0 | I9: 0
A10: Audio/visual + sound system | B10: Buy new | C10: =IF(B10="Buy new",G10,IF(B10="Buy used",H10,0)) | D10: =IF(B10="Lease 60mo",I10,0) | E10: =D10*60 | G10: 5500 | H10: 0 | I10: 0
A11: Locker room fixtures + mirrors | B11: Buy new | C11: =IF(B11="Buy new",G11,IF(B11="Buy used",H11,0)) | D11: =IF(B11="Lease 60mo",I11,0) | E11: =D11*60 | G11: 8500 | H11: 0 | I11: 0
A13: Equipment cash outlay | C13: =SUM(C5:C11)
A14: 60-month lease obligation (total) | E14: =SUM(E5:E11)
A16: Default cost ranges reflect 2026 commercial-grade pricing. Override defaults in columns G-I (hidden) if needed — unhide via Format menu.

Sheet Licensing & Insurance
A1: Licensing, Permits & Insurance — Year 1
A2: Override defaults in blue. Most line items are jurisdiction-dependent.
A4: Line item | B4: Year-1 cost | C4: Notes
A5: LLC / S-Corp formation | B5: 1200 | C5: Filing fees + legal review
A6: Local business license | B6: 800 | C6: Varies by jurisdiction
A7: Building permits | B7: 6000 | C7: Depends on buildout scope
A8: Health & safety permits | B8: 1500
A9: General liability insurance | B9: 5000 | C9: Required before opening
A10: Workers comp insurance | B10: 5000 | C10: Scales with staff count
A11: Property insurance | B11: 2500
A12: Music licensing (ASCAP/BMI/SESAC) | B12: 2500 | C12: Annual; required for any music played
A13: Trademark / brand legal | B13: 2500 | C13: Optional but recommended
A15: Licensing & insurance total | B15: =SUM(B5:B13)

Sheet Software & Tech Stack
A1: Software & Tech Stack — Total Cost of Ownership
A2: Side-by-side comparison: Legacy 2020 stack vs AI-native 2026 stack. Labor offset is where the real money is.
A4: Line item | B4: Legacy stack | C4: AI-native stack | D4: Notes
A5: Gym CRM (MindBody/Glofox/Zen Planner) | B5: 5000 | C5: 3500 | D5: System of record either way
A6: AI agent platform (e.g., fitagentic.ai) | B6: 0 | C6: 7500 | D6: AI-native only
A7: Email marketing (Mailchimp/Klaviyo) | B7: 2500 | C7: 0 | D7: Legacy only — replaced by AI platform
A8: SMS broadcast (Klaviyo SMS/Attentive) | B8: 4000 | C8: 0 | D8: Legacy only — replaced by AI platform
A9: Analytics + reporting add-ons | B9: 2000 | C9: 0 | D9: Legacy only — built into AI platform
A10: Member-facing app | B10: 1500 | C10: 0 | D10: Usually included with AI platform
A11: Software subtotal | B11: =SUM(B5:B10) | C11: =SUM(C5:C10)
A13: Required FTE for admin/lead-handling | D13: Front desk + membership consultant work
A14: FTE count | B14: 2 | C14: 0.5
A15: Fully-loaded cost per FTE (annual) | B15: 45000 | C15: 45000
A16: Annual labor cost | B16: =B14*B15 | C16: =C14*C15
A18: Total Year-1 burden (software + labor) | B18: =B11+B16 | C18: =C11+C16
A20: Year-1 savings going AI-native | B20: =B18-C18
A21: See /how-to-replace-your-gym-front-desk-with-ai-agents for the migration playbook.

Sheet Staff
A1: Staff — Year 1 (excluding admin roles displaced by AI agents)
A2: Override FTE counts and base comp to match your plan. Fully-loaded multiplier defaults to 1.27 (payroll taxes, benefits, workers comp).
A4: Role | B4: FTE count | C4: Annual base comp | D4: Fully-loaded multiplier | E4: Year-1 total cost
A5: Owner-operator | B5: 1 | C5: 80000 | D5: 1.1 | E5: =B5*C5*D5
A6: Studio coordinator / front desk (coverage) | B6: 0.5 | C6: 38000 | D6: 1.27 | E6: =B6*C6*D6
A7: Group fitness instructor | B7: 2 | C7: 28000 | D7: 1.2 | E7: =B7*C7*D7
A8: Personal trainer (employee) | B8: 1 | C8: 50000 | D8: 1.27 | E8: =B8*C8*D8
A9: CrossFit coach | B9: 0 | C9: 35000 | D9: 1.2 | E9: =B9*C9*D9
A10: Studio manager | B10: 0 | C10: 60000 | D10: 1.27 | E10: =B10*C10*D10
A11: GM | B11: 0 | C11: 75000 | D11: 1.3 | E11: =B11*C11*D11
A13: Staff Year-1 total | E13: =SUM(E5:E11)
A15: AI-native lean staffing assumes admin/lead-handling absorbed by AI agents (see Software sheet for the labor offset). See /how-to-hire-gym-staff for full role-design framework.

Sheet Marketing & Launch
A1: Marketing & Launch — Pre-Open + Year 1
A2: Includes pre-sale campaign + Year-1 ongoing marketing. Override defaults to match your plan.
A4: Line item | B4: Cost | C4: Notes
A5: Brand identity (logo, type, color) | B5: 5000 | C5: One-time
A6: Website + landing page build | B6: 7500 | C6: One-time; refresh every 2-3 yr
A7: Photography (interior, member, branded) | B7: 3500 | C7: Refresh annually
A8: Pre-sale Meta ads (90 days) | B8: 6500 | C8: $60-80/day × 90 days
A9: Google Local Service Ads + Search | B9: 4000 | C9: Defensive coverage
A10: Construction signage | B10: 2000 | C10: Best hyperlocal ad you will ever buy
A11: Opening event (food, music, branded swag) | B11: 4500
A12: Year-1 ongoing marketing budget | B12: 22000 | C12: 4-8% of revenue at maturity
A14: Marketing Year-1 total | B14: =SUM(B5:B12)

Sheet Working Capital
A1: Working Capital
A2: The single biggest cause of new-gym failure: running out of cash in months 4–9 before membership ramps. Plan conservatively.
A4: Inputs
A5: Months of operating reserve to fund | B5: ='Format & Scenario'!B18 | C5: Default pulled from scenario selection
A6: Estimated monthly operating cost | B6: =(Staff!E13/12)+(Facility!B5*Facility!B6/12)+('Software & Tech Stack'!C11/12)+('Marketing & Launch'!B14/12) | C6: Auto-computed: staff + rent + software + marketing
A8: Working capital reserve required
A9: Reserve total | B9: =B5*B6
A11: If your model shows breakeven at month 8, fund the cash reserve for breakeven at month 14. Add 50–70% buffer to every revenue assumption.

Sheet Capital Stack Builder
A1: Capital Stack Builder
A2: Input how much each source contributes. Workbook tells you whether you have enough capital to cover total need.
A4: Source | B4: Amount | C4: Notes
A5: SBA 7(a) loan — primary | B5: 140000 | C5: Up to $5M; 10-25 yr terms; ~10-30% down
A6: SBA 504 loan (if buying real estate) | B6: 0 | C6: For real estate purchase only
A7: Equipment lease (60-month obligation) | B7: 45000 | C7: See Equipment sheet for total obligation
A8: Landlord TI absorbed (rolls into rent) | B8: 105000 | C8: Effectively-free buildout capital
A9: Founding-member presale revenue | B9: 30000 | C9: Bridges months 1-3 cash flow
A10: Owner equity injection | B10: 45000 | C10: SBA-required equity stake
A11: Friends & family | B11: 0
A12: ROBS (401k rollover) | B12: 0 | C12: Retirement funds as equity
A13: HELOC / personal credit | B13: 0 | C13: Last resort; pledges home
A14: Other | B14: 0
A16: Total capital available | B16: =SUM(B5:B14)
A18: Total need (from Sensitivity sheet — Realistic scenario) | B18: ='Sensitivity Scenarios'!C8
A19: Funding gap (available minus need) | B19: =B16-B18
A21: Red = you do not have enough capital yet. Green = sources cover need. See /how-to-finance-a-gym for the standard SBA + TI + equipment-lease stack.

Sheet Sensitivity Scenarios
A1: Sensitivity Scenarios
A2: Side-by-side total cost and cash need under four planning scenarios.
A4: Metric | B4: Aggressive | C4: Realistic | D4: Conservative | E4: Stressed
A5: Startup cost (excl. working capital) | B5: =(Facility!B22+Equipment!C13+'Licensing & Insurance'!B15+'Software & Tech Stack'!C11+Staff!E13+'Marketing & Launch'!B14)*0.95 | C5: =(Facility!B22+Equipment!C13+'Licensing & Insurance'!B15+'Software & Tech Stack'!C11+Staff!E13+'Marketing & Launch'!B14) | D5: =(Facility!B22+Equipment!C13+'Licensing & Insurance'!B15+'Software & Tech Stack'!C11+Staff!E13+'Marketing & Launch'!B14)*1.10 | E5: =(Facility!B22+Equipment!C13+'Licensing & Insurance'!B15+'Software & Tech Stack'!C11+Staff!E13+'Marketing & Launch'!B14)*1.25
A6: Working capital reserve | B6: =6*'Working Capital'!B6 | C6: =9*'Working Capital'!B6 | D6: =12*'Working Capital'!B6 | E6: =15*'Working Capital'!B6
A8: TOTAL NEED (cost + working capital) | B8: =B5+B6 | C8: =C5+C6 | D8: =D5+D6 | E8: =E5+E6
A10: Suggested member ramp assumption
A11: Members at month 6 | B11: 120 | C11: 80 | D11: 55 | E11: 35
A12: Members at month 12 | B12: 200 | C12: 140 | D12: 105 | E12: 75
A14: Plan for the Conservative or Stressed column. The cost of overfunding working capital is a small interest expense. The cost of underfunding it is closing.

Sheet Glossary & References
A1: Glossary & References
A3: Key terms
A4: TI (tenant improvement) | B4: Landlord-funded buildout capital amortized into rent. Typical 2026: $20-$80/sq ft for second-gen retail.
A5: CAM (common area maintenance) | B5: Your pro-rata share of landlord costs for the building/center. Push to cap annual increases at 5-7%.
A6: SBA 7(a) | B6: Primary SBA loan instrument for gym financing. Up to $5M, 10-25 year terms, ~10-30% down, prime + 2.75-4.75% rates.
A7: SBA 504 | B7: SBA loan for purchasing long-life fixed assets (typically real estate). Two-loan structure: conventional first (50%), CDC/SBA second (40%), 10% equity.
A8: ARPU | B8: Average revenue per user (per member, per month). Target $110-$160 for boutique, $140-$200 for CrossFit, $35-$70 for full-service.
A9: CAC | B9: Customer acquisition cost. Typical 2026: $80-$150 for boutique studios. Payback under 3 months ARPU is strong.
A10: Payback period | B10: Months of ARPU required to recover CAC. Strong gyms: under 2 months. Typical: 2-4 months.
A11: ROBS | B11: Rollover for Business Startups. Lets you use 401(k)/IRA funds as equity injection without early-withdrawal penalty.
A12: BAA | B12: Business Associate Agreement. Required for any tool handling HIPAA-protected data (only relevant if integrating healthcare data).
A13: Section 179 | B13: IRS provision allowing full deduction of equipment purchases in year of purchase, up to the annual limit. Compare vs lease for tax planning.
A14: Good-guy guarantee | B14: Personal guarantee that limits your liability if you give written notice and vacate by a specified date. Always push for this.
A15: Co-tenancy clause | B15: Right to reduced rent or termination if anchor tenants leave a retail center. Huge if anchor matters to your traffic.
A18: Treetop reference pages
A19: Cost guide | B19: https://treetopgrowthstrategy.com/cost-to-start-a-gym
A20: How to open a gym | B20: https://treetopgrowthstrategy.com/how-to-open-a-gym
A21: How to finance a gym | B21: https://treetopgrowthstrategy.com/how-to-finance-a-gym
A22: How long does it take | B22: https://treetopgrowthstrategy.com/how-long-does-it-take-to-open-a-gym
A23: Lease negotiation | B23: https://treetopgrowthstrategy.com/gym-lease-negotiation-guide
A24: Buy vs lease equipment | B24: https://treetopgrowthstrategy.com/should-i-buy-or-lease-gym-equipment
A25: Pre-sale playbook | B25: https://treetopgrowthstrategy.com/gym-pre-sale-playbook
A26: Membership pricing | B26: https://treetopgrowthstrategy.com/gym-membership-pricing-strategy
A27: Marketing plan | B27: https://treetopgrowthstrategy.com/gym-marketing-plan
A28: Hiring staff | B28: https://treetopgrowthstrategy.com/how-to-hire-gym-staff
A29: Grand opening checklist | B29: https://treetopgrowthstrategy.com/gym-grand-opening-checklist
A30: Replace front desk with AI | B30: https://treetopgrowthstrategy.com/how-to-replace-your-gym-front-desk-with-ai-agents
A31: Free workbook page | B31: https://treetopgrowthstrategy.com/gym-startup-budget-workbook
